preprocessing/__init__.py
visualising/__init__.py
visualising/barcharts.py
KraitUtilities-1.0.0.dist-info/METADATA
KraitUtilities-1.0.0.dist-info/WHEEL
KraitUtilities-1.0.0.dist-info/top_level.txt
KraitUtilities-1.0.0.dist-info/RECORD
